LICENSE
MANIFEST.in
README.md
pylama.ini
pytest.ini
requirements-dev.txt
requirements.txt
setup.py
tox.ini
open_captcha/VERSION
open_captcha/__init__.py
open_captcha/captcha_generator.py
open_captcha/challenge_templates.py
open_captcha/common_types.py
open_captcha.egg-info/PKG-INFO
open_captcha.egg-info/SOURCES.txt
open_captcha.egg-info/dependency_links.txt
open_captcha.egg-info/requires.txt
open_captcha.egg-info/top_level.txt