Metadata-Version: 2.1
Name: open-captcha
Version: 0.1.3
Summary: CAPTCHA challenges generated from your service's data
Home-page: https://github.com/hasadna/OpenCaptcha
Author: Hasadna
Author-email: info@hasadna.org.il
License: MIT
Keywords: CAPTCHA
Platform: UNKNOWN
Classifier: Environment :: Web Environment
Classifier: Intended Audience :: Developers
Classifier: License :: OSI Approved :: MIT License
Classifier: Operating System :: OS Independent
Classifier: Programming Language :: Python :: 3.7
Classifier: Programming Language :: Python :: 3.8
Provides-Extra: develop
